LICENSE
README
setup.py
pyNebula/__init__.py
pyNebula/pyNebula.py
pyNebula.egg-info/PKG-INFO
pyNebula.egg-info/SOURCES.txt
pyNebula.egg-info/dependency_links.txt
pyNebula.egg-info/not-zip-safe
pyNebula.egg-info/top_level.txt